galvani/BioLogic.py
galvani/__init__.py
galvani/res2sqlite.py
galvani-0.3.0.dist-info/GPL-3.0-or-later.txt
galvani-0.3.0.dist-info/METADATA
galvani-0.3.0.dist-info/WHEEL
galvani-0.3.0.dist-info/entry_points.txt
galvani-0.3.0.dist-info/top_level.txt
galvani-0.3.0.dist-info/RECORD
