Metadata-Version: 2.1
Name: galvani
Version: 0.3.0
Summary: Open and process battery charger log data files
Home-page: https://github.com/echemdata/galvani
Author: Chris Kerr
Author-email: chris.kerr@mykolab.ch
License: GPLv3+
Classifier: Development Status :: 4 - Beta
Classifier: Intended Audience :: Developers
Classifier: Intended Audience :: Science/Research
Classifier: License :: OSI Approved :: GNU General Public License v3 or later (GPLv3+)
Classifier: Natural Language :: English
Classifier: Programming Language :: Python :: 3 :: Only
Classifier: Topic :: Scientific/Engineering :: Chemistry
Requires-Python: >=3.6
License-File: LICENSES/GPL-3.0-or-later.txt
Requires-Dist: numpy
